xlsx2pdf/__init__.py
xlsx2pdf/cli.py
xlsx2pdf/transformator.py
xlsx2pdf-1.0.4.dist-info/LICENSE
xlsx2pdf-1.0.4.dist-info/METADATA
xlsx2pdf-1.0.4.dist-info/WHEEL
xlsx2pdf-1.0.4.dist-info/top_level.txt
xlsx2pdf-1.0.4.dist-info/RECORD
