Metadata-Version: 1.2
Name: xlsx2pdf
Version: 1.0.4
Summary: Package converting xlsx spreadsheet to pdf
Home-page: UNKNOWN
Author: INSOFT s.r.o.
Author-email: dosoudil@insoft.cz
License: UNKNOWN
Platform: UNKNOWN
Classifier: Programming Language :: Python :: 3
Classifier: License :: OSI Approved :: MIT License
Classifier: Operating System :: OS Independent
Requires-Python: >=3.6
